[
  {
    "id": "REC-e6823940",
    "name": "Pizza Margherita",
    "description": "Klasická pizza",
    "procedure": "Předehřejte troubu na 220 °C...",
    "ingredients": [
      {
        "id": "ING-239e0305",
        "amount": 50
      },
      {
        "id": "ING-7ecadb7b",
        "amount": 10
      }
    ]
  },
  {
    "id": "REC-1f1ddb76",
    "name": "Pizza XXX",
    "description": "Klasická pizza",
    "procedure": "Předehřejte troubu na 220 °C...",
    "ingredients": [
      {
        "id": "ING-239e0305",
        "amount": 25
      },
      {
        "id": "ING-6ff59e25",
        "amount": 20
      }
    ]
  },
  {
    "id": "REC-63c5eb4c",
    "name": "Pizza TEST",
    "description": "Klasická pizza",
    "procedure": "Předehřejte troubu na 220 °C...",
    "ingredients": [
      {
        "id": "ING-239e0305",
        "amount": 5
      },
      {
        "id": "ING-7c09dfa1",
        "amount": 15
      },
      {
        "id": "ING-6ff59e25",
        "amount": 10
      }
    ]
  }
]